browserbook/__init__.py
browserbook/browserbookcode.py
browserbook/ezbrbk.py
browserbook/tools/URIreader.py
browserbook/tools/canOpener.py
browserbook-0.2.3.dist-info/WHEEL
browserbook-0.2.3.dist-info/METADATA
browserbook-0.2.3.dist-info/RECORD
